sphinx_rtd_theme_github_versions/__init__.py
sphinx_rtd_theme_github_versions/__main__.py
sphinx_rtd_theme_github_versions/_version_git.py
sphinx_rtd_theme_github_versions/layout.html
sphinx_rtd_theme_github_versions/theme.conf
sphinx_rtd_theme_github_versions-1.1.dist-info/LICENSE
sphinx_rtd_theme_github_versions-1.1.dist-info/METADATA
sphinx_rtd_theme_github_versions-1.1.dist-info/WHEEL
sphinx_rtd_theme_github_versions-1.1.dist-info/entry_points.txt
sphinx_rtd_theme_github_versions-1.1.dist-info/top_level.txt
sphinx_rtd_theme_github_versions-1.1.dist-info/RECORD
