Metadata-Version: 2.1
Name: sphinx-rtd-theme-github-versions
Version: 1.1
Summary: Sphinx readthedocs theme with support for documentation versions from github.io
Home-page: https://github.com/dls-controls/sphinx_rtd_theme_github_versions
Author: Tom Cobb
Author-email: tom.cobb@diamond.ac.uk
License: Apache License 2.0
Platform: UNKNOWN
Classifier: Development Status :: 4 - Beta
Classifier: License :: OSI Approved :: Apache Software License
Classifier: Programming Language :: Python :: 3.7
Classifier: Programming Language :: Python :: 3.8
Classifier: Programming Language :: Python :: 3.9
Requires-Python: >=3.7
Requires-Dist: sphinx-rtd-theme
Provides-Extra: dev
Requires-Dist: black (==21.9b0) ; extra == 'dev'
Requires-Dist: isort (>5.0) ; extra == 'dev'
Requires-Dist: pytest-cov ; extra == 'dev'
Requires-Dist: mypy ; extra == 'dev'
Requires-Dist: flake8-isort ; extra == 'dev'
Requires-Dist: pre-commit ; extra == 'dev'
Requires-Dist: types-docutils ; extra == 'dev'
